consensual/__init__.py
consensual/raft.py
consensual/core/__init__.py
consensual/core/raft/__init__.py
consensual/core/raft/cluster.py
consensual/core/raft/cluster_id.py
consensual/core/raft/command.py
consensual/core/raft/communication.py
consensual/core/raft/hints.py
consensual/core/raft/history.py
consensual/core/raft/messages.py
consensual/core/raft/node.py
consensual/core/raft/receiver.py
consensual/core/raft/record.py
consensual/core/raft/role.py
consensual/core/raft/sender.py
consensual/core/raft/utils.py
consensual-0.2.3.dist-info/LICENSE
consensual-0.2.3.dist-info/METADATA
consensual-0.2.3.dist-info/WHEEL
consensual-0.2.3.dist-info/top_level.txt
consensual-0.2.3.dist-info/RECORD
