Metadata-Version: 2.1
Name: consensual
Version: 0.2.3
Summary: Implementation of raft consensus algorithm.
Home-page: https://github.com/lycantropos/consensual/
Download-URL: https://github.com/lycantropos/consensual/archive/master.zip
Author: Azat Ibrakov
Author-email: azatibrakov@gmail.com
License: MIT License
Platform: UNKNOWN
Classifier: License :: OSI Approved :: MIT License
Classifier: Programming Language :: Python :: 3.7
Classifier: Programming Language :: Python :: 3.8
Classifier: Programming Language :: Python :: 3.9
Classifier: Programming Language :: Python :: 3.10
Classifier: Programming Language :: Python :: Implementation :: CPython
Requires-Python: >=3.7
License-File: LICENSE
Requires-Dist: reprit (<1.0,>=0.6.0)
Requires-Dist: yarl (<2.0,>=1.7.2)
Requires-Dist: typing-extensions (<5.0,>=4.0.1) ; python_version < "3.8"
